document_tracking_resources/__init__.py
document_tracking_resources/corpus.py
document_tracking_resources/documents.py
document_tracking_resources-1.0.1.202209211711.dist-info/AUTHORS
document_tracking_resources-1.0.1.202209211711.dist-info/LICENSE
document_tracking_resources-1.0.1.202209211711.dist-info/METADATA
document_tracking_resources-1.0.1.202209211711.dist-info/WHEEL
document_tracking_resources-1.0.1.202209211711.dist-info/top_level.txt
document_tracking_resources-1.0.1.202209211711.dist-info/RECORD
