Metadata-Version: 2.1
Name: document-tracking-resources
Version: 1.0.1.202209211711
Summary: Package to load the resources required by the document_tracking package.
Home-page: https://gitlab.univ-lr.fr/cross-lingual-event-tracking/developpement/from-documents-to-events/documents_tracking_resources
Author: Guillaume Bernard
Author-email: contact@guillaume-bernard.fr
License: UNKNOWN
Project-URL: Bug Tracker, https://gitlab.univ-lr.fr/cross-lingual-event-tracking/developpement/from-documents-to-events/documents_tracking_resources/-/issues
Platform: UNKNOWN
Classifier: Programming Language :: Python :: 3.9
Classifier: License :: OSI Approved :: GNU General Public License v3 (GPLv3)
Classifier: Operating System :: POSIX :: Linux
Classifier: Topic :: Scientific/Engineering :: Artificial Intelligence
Classifier: Intended Audience :: Science/Research
License-File: LICENSE
License-File: AUTHORS
Requires-Dist: numpy (>=1.22.0)
Requires-Dist: pandas (>=1.5.0)
Requires-Dist: setuptools (>=59.6.0)
